deepsensemaking/__init__.py
deepsensemaking/_version.py
deepsensemaking/base/__init__.py
deepsensemaking/bids/__init__.py
deepsensemaking/dicts/__init__.py
deepsensemaking/eeg/__init__.py
deepsensemaking/eeg/mne/__init__.py
deepsensemaking/eeg/mne/backup_001.py
deepsensemaking/info/__init__.py
deepsensemaking/jiko/__init__.py
deepsensemaking/ml/__init__.py
deepsensemaking/nlp/__init__.py
deepsensemaking/nlp/yaliwc/__init__.py
deepsensemaking/nlp/yaliwc/dict/ejsp2561_big2a_agency.py
deepsensemaking/nlp/yaliwc/dict/ejsp2561_big2a_commun.py
deepsensemaking/nlp/yaliwc/dict/ejsp2561_big2b_agency.py
deepsensemaking/nlp/yaliwc/dict/ejsp2561_big2b_commun.py
deepsensemaking/nlp/yaliwc/dict/emoji_basic.py
deepsensemaking/nlp/yaliwc/dict/testing_words.py
deepsensemaking/nlp/yaliwc/legacy/__init__.py
deepsensemaking/nlp/yaliwc/legacy/dict/ejsp2561_big2a_agency.py
deepsensemaking/nlp/yaliwc/legacy/dict/ejsp2561_big2a_commun.py
deepsensemaking/nlp/yaliwc/legacy/dict/ejsp2561_big2b_agency.py
deepsensemaking/nlp/yaliwc/legacy/dict/ejsp2561_big2b_commun.py
deepsensemaking/nlp/yaliwc/legacy/dict/sample_dummy.py
deepsensemaking/nlp/yaliwc/legacy/dict/sample_dummy_docs.py
deepsensemaking/nlp/yaliwc/legacy/dict/sample_emoji.py
deepsensemaking/pd/__init__.py
deepsensemaking/recursions/__init__.py
deepsensemaking/strings/__init__.py
deepsensemaking/temp/__init__.py
deepsensemaking/within/__init__.py
deepsensemaking-0.1.2021.1.11.5.data/scripts/deepsensemaking-cli
deepsensemaking-0.1.2021.1.11.5.data/scripts/dsm-cli-old-bids-helper
deepsensemaking-0.1.2021.1.11.5.data/scripts/dsm-cli-old-eeg-bp-meta
deepsensemaking-0.1.2021.1.11.5.dist-info/LICENSE.txt
deepsensemaking-0.1.2021.1.11.5.dist-info/METADATA
deepsensemaking-0.1.2021.1.11.5.dist-info/WHEEL
deepsensemaking-0.1.2021.1.11.5.dist-info/top_level.txt
deepsensemaking-0.1.2021.1.11.5.dist-info/RECORD
