Metadata-Version: 2.1
Name: deepsensemaking
Version: 0.1.2021.1.11.5
Summary: deepsensemaking (dsm)
Home-page: https://github.com/deepsensemaking/deepsensemaking
Author: DeepSenseMaking Developes
Author-email: deepsensemaking@gmail.com
License: Apache License 2.0
Download-URL: https://github.com/deepsensemaking/deepsensemaking/releases/download/0.1.2020.5.17.1/deepsensemaking-0.1.2020.5.17.1-py3-none-any.whl
Keywords: deepsensemaking,deep,sensemaking,natural language processing,nlp,machine learning,ml,artificial intelligence,ai,signals intelligence,sigint,communications intelligence,comint
Platform: UNKNOWN
Classifier: Environment :: Console
Classifier: Natural Language :: English
Classifier: Operating System :: OS Independent
Classifier: Intended Audience :: Science/Research
Classifier: Development Status :: 2 - Pre-Alpha
Classifier: Programming Language :: Python :: 3.6
Classifier: License :: OSI Approved :: Apache Software License
Requires-Python: >=3.6
Requires-Dist: argparse (>=1.1)
Requires-Dist: pandas (>=1.0.1)
Requires-Dist: numpy (>=1.18.1)
Requires-Dist: scipy (>=1.4.1)
Requires-Dist: colorama (>=0.4.3)
